README.md
setup.py
bscscan/__init__.py
bscscan/accounts.py
bscscan/client.py
bscscan/contracts.py
bscscan/stats.py
bscscan/tokens.py
examples/__init__.py
examples/accounts/__init__.py
examples/accounts/get_all_blocks_mined.py
examples/accounts/get_all_transactions.py
examples/accounts/get_balance.py
examples/accounts/get_balance_multi.py
examples/accounts/get_blocks_mined.py
examples/accounts/get_transaction_page.py
examples/accounts/get_transaction_page_erc20.py
examples/stats/__init__.py
examples/stats/get_bnb_last_price.py
examples/stats/get_total_bnb_supply.py
examples/stats/get_validators.py
examples/tokens/__init__.py
examples/tokens/get_token_balance.py
examples/tokens/get_total_supply.py
py_bscscan_api.egg-info/PKG-INFO
py_bscscan_api.egg-info/SOURCES.txt
py_bscscan_api.egg-info/dependency_links.txt
py_bscscan_api.egg-info/requires.txt
py_bscscan_api.egg-info/top_level.txt